Metadata-Version: 2.4
Name: SleePyPhases
Version: 0.6.0
Summary: A framwork for creating deep learning pipelines for sleep data
Home-page: https://gitlab.com/sleep-is-all-you-need/sleepyphases
Author: Franz Ehrlich
Author-email: fehrlichd@gmail.com
Classifier: Programming Language :: Python :: 3
Classifier: License :: OSI Approved :: MIT License
Classifier: Operating System :: OS Independent
Requires-Python: >=3.5
License-File: LICENSE
Requires-Dist: SleepHarmonizer
Requires-Dist: pyPhasesML
Requires-Dist: phases
Dynamic: author
Dynamic: author-email
Dynamic: classifier
Dynamic: description
Dynamic: description-content-type
Dynamic: home-page
Dynamic: license-file
Dynamic: requires-dist
Dynamic: requires-python
Dynamic: summary
